LICENSE
MANIFEST.in
README.md
setup.cfg
setup.py
tap_facebook/__init__.py
tap_facebook/insights_experiment.py
tap_facebook/process_output.py
tap_facebook.egg-info/PKG-INFO
tap_facebook.egg-info/SOURCES.txt
tap_facebook.egg-info/dependency_links.txt
tap_facebook.egg-info/entry_points.txt
tap_facebook.egg-info/requires.txt
tap_facebook.egg-info/top_level.txt
tap_facebook/schemas/adcreative.json
tap_facebook/schemas/ads.json
tap_facebook/schemas/ads_insights.json
tap_facebook/schemas/ads_insights_age_and_gender.json
tap_facebook/schemas/ads_insights_country.json
tap_facebook/schemas/ads_insights_dma.json
tap_facebook/schemas/ads_insights_hourly_advertiser.json
tap_facebook/schemas/ads_insights_platform_and_device.json
tap_facebook/schemas/ads_insights_region.json
tap_facebook/schemas/adsets.json
tap_facebook/schemas/campaigns.json
tap_facebook/schemas/leads.json
tap_facebook/schemas/shared/ads_action_stats.json
tap_facebook/schemas/shared/ads_histogram_stats.json
tap_facebook/schemas/shared/ads_image_crops.json
tap_facebook/schemas/shared/geo_locations.json
tap_facebook/schemas/shared/targeting.json
tests/test_client.py
tests/test_facebook_all_fields.py
tests/test_facebook_archived_data.py
tests/test_facebook_attribution_window.py
tests/test_facebook_automatic_fields.py
tests/test_facebook_bookmarks.py
tests/test_facebook_discovery.py
tests/test_facebook_field_selection.py
tests/test_facebook_invalid_attribution_window.py
tests/test_facebook_pagination.py
tests/test_facebook_start_date.py
tests/test_facebook_table_reset.py