Metadata-Version: 2.4
Name: tap-facebook
Version: 1.22.0
Summary: Singer.io tap for extracting data from the Facebook Ads API
Home-page: https://singer.io
Author: Stitch
Classifier: Programming Language :: Python :: 3 :: Only
License-File: LICENSE
Requires-Dist: attrs==17.3.0
Requires-Dist: backoff==2.2.1
Requires-Dist: facebook_business==21.0.5
Requires-Dist: pendulum==1.2.0
Requires-Dist: requests==2.20.0
Requires-Dist: singer-python==6.0.0
Provides-Extra: dev
Requires-Dist: pylint; extra == "dev"
Requires-Dist: ipdb; extra == "dev"
Requires-Dist: nose; extra == "dev"
Dynamic: author
Dynamic: classifier
Dynamic: home-page
Dynamic: license-file
Dynamic: provides-extra
Dynamic: requires-dist
Dynamic: summary
